llm_bedrock_titan.py
llm_bedrock_amazon-1.0.1.dist-info/LICENSE
llm_bedrock_amazon-1.0.1.dist-info/METADATA
llm_bedrock_amazon-1.0.1.dist-info/WHEEL
llm_bedrock_amazon-1.0.1.dist-info/entry_points.txt
llm_bedrock_amazon-1.0.1.dist-info/top_level.txt
llm_bedrock_amazon-1.0.1.dist-info/RECORD
