Metadata-Version: 2.1
Name: llm-bedrock-amazon
Version: 1.0.1
Summary: LLM plugin for Amazon Titan on AWS Bedrock
Author: Sean Blakey, Will Sorenson, Viacheslav Vasilyev
License: Apache-2.0
Project-URL: Homepage, https://github.com/avoidik/llm-bedrock-amazon
Classifier: License :: OSI Approved :: Apache Software License
License-File: LICENSE
Requires-Dist: llm
Requires-Dist: boto3 >=1.34.55
Requires-Dist: pydantic >=2.0
